underdogcowboy/.DS_Store
underdogcowboy/__init__.py
underdogcowboy/file.log
underdogcowboy/main.py
underdogcowboy/pre-release-nov-dec-2024.log
underdogcowboy/run_timeline_editor.py
underdogcowboy/traverse.py
underdogcowboy/agents/__init__.py
underdogcowboy/agents/meta/agentclarity.json
underdogcowboy/agents/meta/assessmentbuilder.json
underdogcowboy/core/__init__.py
underdogcowboy/core/agent.py
underdogcowboy/core/config_manager.py
underdogcowboy/core/dialog_manager.py
underdogcowboy/core/exceptions.py
underdogcowboy/core/extractor.py
underdogcowboy/core/intervention.py
underdogcowboy/core/json_storage.py
underdogcowboy/core/llm_response_markdown.py
underdogcowboy/core/markdown_pre_processor.py
underdogcowboy/core/model.py
underdogcowboy/core/response.py
underdogcowboy/core/specialized_agents.py
underdogcowboy/core/timeline_editor.py
underdogcowboy/core/tracing.py
underdogcowboy/core/uc_agent_communicator.py
underdogcowboy/core/commandtools/__init__.py
underdogcowboy/core/commandtools/agent_clarity.py
underdogcowboy/core/commandtools/agent_llm_handler.py
underdogcowboy/core/commandtools/agent_pdf.py
underdogcowboy/core/commandtools/assessment_agent_builder.py
underdogcowboy/core/commandtools/llm_config.py
underdogcowboy/core/commandtools/modular.py
underdogcowboy/core/commandtools/poke.py
underdogcowboy/core/commandtools/tracing_config.py
underdogcowboy/core/commandtools/agent_flow/.mdformat.toml
underdogcowboy/core/commandtools/agent_flow/__init__.py
underdogcowboy/core/commandtools/agent_flow/agent_llm_handler.py
underdogcowboy/core/commandtools/agent_flow/app.py
underdogcowboy/core/commandtools/agent_flow/config.py
underdogcowboy/core/commandtools/agent_flow/config.yaml
underdogcowboy/core/commandtools/agent_flow/copy_paste.py
underdogcowboy/core/commandtools/agent_flow/exceptions.py
underdogcowboy/core/commandtools/agent_flow/llm_call_manager.py
underdogcowboy/core/commandtools/agent_flow/llm_manager.py
underdogcowboy-0.1.14.14.dist-info/METADATA
underdogcowboy-0.1.14.14.dist-info/WHEEL
underdogcowboy-0.1.14.14.dist-info/entry_points.txt
underdogcowboy-0.1.14.14.dist-info/top_level.txt
underdogcowboy-0.1.14.14.dist-info/RECORD
