Metadata-Version: 2.1
Name: underdogcowboy
Version: 0.1.14.14
Summary: Underdog Cowboy (UC): Wrangle Your LLMs with a Smile
License: MIT
Requires-Python: >=3.7
Requires-Dist: vertexai
Requires-Dist: prompt_toolkit
Requires-Dist: python-dotenv
Requires-Dist: keyring
Requires-Dist: groq
Requires-Dist: langsmith
Requires-Dist: reportlab
Requires-Dist: pillow
Requires-Dist: requests-mock
Requires-Dist: rich
Requires-Dist: mdformat
Requires-Dist: textual
Requires-Dist: pyyaml
Requires-Dist: pyperclip
Requires-Dist: uccli>=0.0.5.1
